pyprotonrebar/__init__.py
pyprotonrebar/pyrackndr.py
pyrackndr/__init__.py
pyrackndr/pyrackndr.py
pyprotonrebar-0.0.1.dist-info/AUTHORS.rst
pyprotonrebar-0.0.1.dist-info/LICENSE
pyprotonrebar-0.0.1.dist-info/METADATA
pyprotonrebar-0.0.1.dist-info/WHEEL
pyprotonrebar-0.0.1.dist-info/top_level.txt
pyprotonrebar-0.0.1.dist-info/RECORD
