Metadata-Version: 2.1
Name: pyprotonrebar
Version: 0.0.1
Summary: Interact with the RackN Digital Rebar API
Home-page: https://github.com/ProtonMail/pyprotonrebar
Author: Sorin-Alexandru Paduraru
Author-email: spaduraru@proton.ch
License: Apache-2.0
Project-URL: Changelog, https://github.com/ProtonMail/pyprotonrebar/blob/master/CHANGELOG.rst
Project-URL: Issue Tracker, https://github.com/ProtonMail/pyprotonrebar/issues
Classifier: Development Status :: 5 - Production/Stable
Classifier: Intended Audience :: Developers
Classifier: License :: OSI Approved :: Apache Software License
Classifier: Operating System :: Unix
Classifier: Operating System :: POSIX
Classifier: Operating System :: Microsoft :: Windows
Classifier: Programming Language :: Python
Classifier: Programming Language :: Python :: 3
Classifier: Programming Language :: Python :: 3 :: Only
Classifier: Programming Language :: Python :: 3.8
Classifier: Programming Language :: Python :: 3.9
Classifier: Programming Language :: Python :: 3.10
Classifier: Programming Language :: Python :: 3.11
Classifier: Programming Language :: Python :: 3.12
Classifier: Programming Language :: Python :: Implementation :: CPython
Classifier: Programming Language :: Python :: Implementation :: PyPy
Classifier: Topic :: Utilities
Requires-Python: >=3.8
License-File: LICENSE
License-File: AUTHORS.rst
Requires-Dist: jsonpatch >=1.33
Requires-Dist: requests >=2.31.0
